{"importBase":"import","nativeBase":"native","name":"main","deps":["internal"],"uuids":["028e34ddc","042807bce","0699aaa4c","06add430f","0f4f09600","8aVGk1cNRC0qBRjQ528oAI","d1m4qB48xEqaykPzPY+7cN","baIUdvKGZPgZxNbjWTFuRI","6fAc9/gb9Kfr1dCvwZaWSA@b47c0","6fAc9/gb9Kfr1dCvwZaWSA@b47c0@40c10","6fAc9/gb9Kfr1dCvwZaWSA@b47c0@74afd","6fAc9/gb9Kfr1dCvwZaWSA@b47c0@7d38f","6fAc9/gb9Kfr1dCvwZaWSA@b47c0@8fd34","6fAc9/gb9Kfr1dCvwZaWSA@b47c0@bb97f","6fAc9/gb9Kfr1dCvwZaWSA@b47c0@e9a6d","70D6oXEaZGza611pALwmT4","70D6oXEaZGza611pALwmT4@6c48a","70D6oXEaZGza611pALwmT4@f9941","79bQkkC8xBObOzvjYcuzlq","79bQkkC8xBObOzvjYcuzlq@6c48a","79bQkkC8xBObOzvjYcuzlq@f9941","80D5T9dCRCApYp08p387ct","9ecey8jWNF3bDjJs76PQex","9ecey8jWNF3bDjJs76PQex@6c48a","9ecey8jWNF3bDjJs76PQex@f9941","a3U2ErrBNHlq9KanvGvihl","a3U2ErrBNHlq9KanvGvihl@6c48a","a3U2ErrBNHlq9KanvGvihl@f9941","aeTiGIK3tCqYXhj7mHYAsE","aeTiGIK3tCqYXhj7mHYAsE@6c48a","aeTiGIK3tCqYXhj7mHYAsE@f9941","c151es9btG7bhq/av/eutV","c151es9btG7bhq/av/eutV@6c48a","c151es9btG7bhq/av/eutV@f9941","d0MqyYBeFAkIi762QNy1/B@b47c0","d0MqyYBeFAkIi762QNy1/B@b47c0@40c10","d0MqyYBeFAkIi762QNy1/B@b47c0@74afd","d0MqyYBeFAkIi762QNy1/B@b47c0@7d38f","d0MqyYBeFAkIi762QNy1/B@b47c0@8fd34","d0MqyYBeFAkIi762QNy1/B@b47c0@bb97f","d0MqyYBeFAkIi762QNy1/B@b47c0@e9a6d","ed2XmIUqNDEoZxkKUbtWOu","ed2XmIUqNDEoZxkKUbtWOu@6c48a","ed2XmIUqNDEoZxkKUbtWOu@f9941","fdjsU2o1RKF5x0TziDw3jI"],"paths":{"5":["db:/assets/scenes/menu",0,1],"6":["db:/assets/scenes/MainScene",0,1],"7":["db:/internal/physics/default-physics-material",2,1],"44":["db:/internal/default_renderpipeline/builtin-forward",1,1]},"scenes":{"db://assets/scenes/MainScene.scene":6,"db://assets/scenes/menu.scene":5},"packs":{"028e34ddc":[20,27,6],"042807bce":[23,16,19,26,29,32,42],"0699aaa4c":[8,9,10,11,12,13,14],"06add430f":[34,35,36,37,38,39,40],"0f4f09600":[17,21,5,24,30,33,43]},"versions":{"import":[],"native":[]},"redirect":[7,"0"],"debug":false,"extensionMap":{},"hasPreloadScript":true,"dependencyRelationships":{},"types":["cc.SceneAsset","cc.RenderPipeline","cc.PhysicsMaterial"]}